bitbazaar/__init__.py
bitbazaar/_testing.py
bitbazaar/py.typed
bitbazaar/log/__init__.py
bitbazaar/log/_exporters.py
bitbazaar/log/_file_handler.py
bitbazaar/log/_formatting.py
bitbazaar/log/_global_log.py
bitbazaar/log/_setup.py
bitbazaar/log/_utils.py
bitbazaar/misc/__init__.py
bitbazaar/misc/_std_capture.py
bitbazaar/testing/__init__.py
bitbazaar/testing/_tmp_file_manager.py
bitbazaar-0.0.7.dist-info/METADATA
bitbazaar-0.0.7.dist-info/WHEEL
bitbazaar-0.0.7.dist-info/licenses/LICENSE.md
bitbazaar-0.0.7.dist-info/licenses/LICENSE.zetch.md
bitbazaar-0.0.7.dist-info/RECORD
