Metadata-Version: 2.1
Name: bitbazaar
Version: 0.0.7
Summary: An assortment of publicly available cross-language utilities useful to my projects.
Project-URL: Sourcecode, https://github.com/zakstucke/bitbazaar
Project-URL: Documentation, https://zakstucke.github.io/bitbazaar
Author-email: Zachary Stucke <zakstucke@gmail.com>
License: MIT
License-File: LICENSE.md
License-File: LICENSE.zetch.md
Classifier: Development Status :: 1 - Planning
Classifier: License :: OSI Approved
Classifier: Operating System :: MacOS
Classifier: Operating System :: Microsoft :: Windows
Classifier: Operating System :: POSIX :: Linux
Classifier: Programming Language :: Python
Classifier: Programming Language :: Python :: 3
Classifier: Programming Language :: Python :: 3 :: Only
Classifier: Programming Language :: Python :: 3.11
Classifier: Programming Language :: Python :: 3.12
Classifier: Programming Language :: Python :: Implementation :: CPython
Classifier: Typing :: Typed
Requires-Python: >=3.11
Requires-Dist: lazy-object-proxy>=1.8.0
Requires-Dist: opentelemetry-api>=1.20.0
Requires-Dist: opentelemetry-exporter-otlp>=1.20.0
Requires-Dist: opentelemetry-sdk>=1.20.0
Requires-Dist: rich>=13.6.0
